LICENSE
MANIFEST.in
README.md
requirements.txt
setup.py
muto_server.egg-info/PKG-INFO
muto_server.egg-info/SOURCES.txt
muto_server.egg-info/dependency_links.txt
muto_server.egg-info/not-zip-safe
muto_server.egg-info/requires.txt
muto_server.egg-info/top_level.txt
mutoserver/__init__.py
mutoserver/admin.py
mutoserver/models.py
mutoserver/tests.py
mutoserver/views.py
mutoserver/management/__init__.py
mutoserver/management/commands/__init__.py
mutoserver/management/commands/watchqueue.py